{
 "curriculum": "Home & Daily Life",
 "group": "Home & Daily Life",
 "list_id": "home-list01",
 "list_name": "Home & Objects",
 "cards": [
  {
   "id": "home-l01-001",
   "front": "部屋",
   "reading": "へや",
   "meaning_zh": "房间",
   "meaning_en": "room",
   "meaning_ja": "へや",
   "explain_zh": "指房间，如卧室、客厅或任何被墙壁隔开的空间。\n\n例：この部屋は明るいです。\n这个房间很明亮。",
   "explain_en": "Refers to a room, such as a bedroom, living room, or any space separated by walls.\n\n例：この部屋は明るいです。\nThis room is bright.",
   "explain_ja": "建物の中で壁で仕切られた空間。寝室や居間などに使う。\n\n例：この部屋は明るいです。",
   "audio_anime": null,
   "audio_announcer": null,
   "audio_example": null,
   "duplicate_of": null,
   "extra": "",
   "audio": {
    "aoyama": "sample/audio/home-l01-001/aoyama.mp3",
    "kyushu": "sample/audio/home-l01-001/kyushu.mp3",
    "yurei": "sample/audio/home-l01-001/yurei.mp3",
    "zunda": "sample/audio/home-l01-001/zunda.mp3",
    "no7": "sample/audio/home-l01-001/no7.mp3",
    "metan": "sample/audio/home-l01-001/metan.mp3"
   }
  },
  {
   "id": "home-l01-002",
   "front": "机",
   "reading": "つくえ",
   "meaning_zh": "桌子",
   "meaning_en": "desk",
   "meaning_ja": "つくえ",
   "explain_zh": "指书桌或桌子，通常用于学习或办公。\n\n例：机の上に本があります。\n桌子上有书。",
   "explain_en": "Refers to desk or table, typically used for studying or working.\n\n例：机の上に本があります。\nThere is a book on the desk.",
   "explain_ja": "勉強や仕事に使う家具。脚と天板からなる。\n\n例：机の上に本があります。",
   "audio_anime": null,
   "audio_announcer": null,
   "audio_example": null,
   "duplicate_of": null,
   "extra": "",
   "audio": {
    "aoyama": "sample/audio/home-l01-002/aoyama.mp3",
    "kyushu": "sample/audio/home-l01-002/kyushu.mp3",
    "yurei": "sample/audio/home-l01-002/yurei.mp3",
    "zunda": "sample/audio/home-l01-002/zunda.mp3",
    "no7": "sample/audio/home-l01-002/no7.mp3",
    "metan": "sample/audio/home-l01-002/metan.mp3"
   }
  },
  {
   "id": "home-l01-003",
   "front": "椅子",
   "reading": "いす",
   "meaning_zh": "椅子",
   "meaning_en": "chair",
   "meaning_ja": "いす",
   "explain_zh": "指用来坐的家具，通常有腿和靠背。\n\n例：この椅子はとても座りやすいです。\n这张椅子坐起来很舒服。",
   "explain_en": "A piece of furniture for sitting on, typically with legs and a backrest.\n\n例：この椅子はとても座りやすいです。\nThis chair is very comfortable to sit on.",
   "explain_ja": "人が座るための家具で、脚や背もたれがあるのが一般的です。\n\n例：この椅子はとても座りやすいです。",
   "audio_anime": null,
   "audio_announcer": null,
   "audio_example": null,
   "duplicate_of": null,
   "extra": "",
   "audio": {
    "aoyama": "sample/audio/home-l01-003/aoyama.mp3",
    "kyushu": "sample/audio/home-l01-003/kyushu.mp3",
    "yurei": "sample/audio/home-l01-003/yurei.mp3",
    "zunda": "sample/audio/home-l01-003/zunda.mp3",
    "no7": "sample/audio/home-l01-003/no7.mp3",
    "metan": "sample/audio/home-l01-003/metan.mp3"
   }
  },
  {
   "id": "home-l01-004",
   "front": "ドア",
   "reading": "ドア",
   "meaning_zh": "门",
   "meaning_en": "door",
   "meaning_ja": "ドア",
   "explain_zh": "指建筑或房间的入口处可开关的板状物体，常用作进出通道。\n\n例：ドアを開けてください。\n请开门。",
   "explain_en": "A movable barrier at the entrance of a building or room, used for opening and closing.\n\n例：ドアを開けてください。\nPlease open the door.",
   "explain_ja": "建物や部屋の出入り口にはめられた、開け閉めできる板状のものです。\n\n例：ドアを開けてください。",
   "audio_anime": null,
   "audio_announcer": null,
   "audio_example": null,
   "duplicate_of": null,
   "extra": "",
   "audio": {
    "aoyama": "sample/audio/home-l01-004/aoyama.mp3",
    "kyushu": "sample/audio/home-l01-004/kyushu.mp3",
    "yurei": "sample/audio/home-l01-004/yurei.mp3",
    "zunda": "sample/audio/home-l01-004/zunda.mp3",
    "no7": "sample/audio/home-l01-004/no7.mp3",
    "metan": "sample/audio/home-l01-004/metan.mp3"
   }
  },
  {
   "id": "home-l01-005",
   "front": "窓",
   "reading": "まど",
   "meaning_zh": "窗户",
   "meaning_en": "window",
   "meaning_ja": "まど",
   "explain_zh": "指墙壁上用来采光、通风的开口，通常装有玻璃。\n\n例：窓から外を見ます。\n从窗户看外面。",
   "explain_en": "An opening in a wall fitted with glass or other material, used to let in light and air.\n\n例：窓から外を見ます。\nI look outside through the window.",
   "explain_ja": "壁に設けられた開口部で、光や風を通すためにガラスなどがはめてあります。\n\n例：窓から外を見ます。",
   "audio_anime": null,
   "audio_announcer": null,
   "audio_example": null,
   "duplicate_of": null,
   "extra": "",
   "audio": {
    "aoyama": "sample/audio/home-l01-005/aoyama.mp3",
    "kyushu": "sample/audio/home-l01-005/kyushu.mp3",
    "yurei": "sample/audio/home-l01-005/yurei.mp3",
    "zunda": "sample/audio/home-l01-005/zunda.mp3",
    "no7": "sample/audio/home-l01-005/no7.mp3",
    "metan": "sample/audio/home-l01-005/metan.mp3"
   }
  },
  {
   "id": "home-l01-006",
   "front": "電話",
   "reading": "でんわ",
   "meaning_zh": "电话",
   "meaning_en": "telephone",
   "meaning_ja": "でんわ",
   "explain_zh": "指利用电信号传输声音或文字的通信设备。\n\n例：電話で友達と話します。\n用电话和朋友说话。",
   "explain_en": "A communication device that transmits sound or text using electrical signals.\n\n例：電話で友達と話します。\nI talk with my friend on the phone.",
   "explain_ja": "電気信号を使って音声や文字をやり取りする通信機器です。\n\n例：電話で友達と話します。",
   "audio_anime": null,
   "audio_announcer": null,
   "audio_example": null,
   "duplicate_of": null,
   "extra": "",
   "audio": {
    "aoyama": "sample/audio/home-l01-006/aoyama.mp3",
    "kyushu": "sample/audio/home-l01-006/kyushu.mp3",
    "yurei": "sample/audio/home-l01-006/yurei.mp3",
    "zunda": "sample/audio/home-l01-006/zunda.mp3",
    "no7": "sample/audio/home-l01-006/no7.mp3",
    "metan": "sample/audio/home-l01-006/metan.mp3"
   }
  },
  {
   "id": "home-l01-007",
   "front": "時計",
   "reading": "とけい",
   "meaning_zh": "钟 / 表",
   "meaning_en": "clock / watch",
   "meaning_ja": "とけい",
   "explain_zh": "指用来显示时间的工具，可以挂在墙上或戴在手腕上。\n\n例：この時計はとても正確です。\n这个钟/表非常准确。",
   "explain_en": "An instrument that shows the time, often hung on a wall or worn on the wrist.\n\n例：この時計はとても正確です。\nThis clock/watch is very accurate.",
   "explain_ja": "時間を示す道具で、壁にかけるものや腕に着けるものがあります。\n\n例：この時計はとても正確です。",
   "audio_anime": null,
   "audio_announcer": null,
   "audio_example": null,
   "duplicate_of": null,
   "extra": "",
   "audio": {
    "aoyama": "sample/audio/home-l01-007/aoyama.mp3",
    "kyushu": "sample/audio/home-l01-007/kyushu.mp3",
    "yurei": "sample/audio/home-l01-007/yurei.mp3",
    "zunda": "sample/audio/home-l01-007/zunda.mp3",
    "no7": "sample/audio/home-l01-007/no7.mp3",
    "metan": "sample/audio/home-l01-007/metan.mp3"
   }
  },
  {
   "id": "home-l01-008",
   "front": "本",
   "reading": "ほん",
   "meaning_zh": "书",
   "meaning_en": "book",
   "meaning_ja": "ほん",
   "explain_zh": "指由纸质或电子页面装订而成、用于阅读或参考的文字作品。\n\n例：この本はとても面白いです。\n这本书很有趣。",
   "explain_en": "A written work consisting of pages bound together, used for reading or reference.\n\n例：この本はとても面白いです。\nThis book is very interesting.",
   "explain_ja": "紙や電子のページをまとめた、読んだり調べたりするためのものです。\n\n例：この本はとても面白いです。",
   "audio_anime": null,
   "audio_announcer": null,
   "audio_example": null,
   "duplicate_of": null,
   "extra": "",
   "audio": {
    "aoyama": "sample/audio/home-l01-008/aoyama.mp3",
    "kyushu": "sample/audio/home-l01-008/kyushu.mp3",
    "yurei": "sample/audio/home-l01-008/yurei.mp3",
    "zunda": "sample/audio/home-l01-008/zunda.mp3",
    "no7": "sample/audio/home-l01-008/no7.mp3",
    "metan": "sample/audio/home-l01-008/metan.mp3"
   }
  },
  {
   "id": "home-l01-009",
   "front": "鍵",
   "reading": "かぎ",
   "meaning_zh": "钥匙",
   "meaning_en": "key",
   "meaning_ja": "かぎ",
   "explain_zh": "指用来锁或开锁的小型金属工具，通常带齿状边。\n\n例：鍵を忘れました。\n我忘了钥匙。",
   "explain_en": "A small metal tool used to lock or unlock a lock, often with a toothed edge.\n\n例：鍵を忘れました。\nI forgot the key.",
   "explain_ja": "錠前を閉めたり開けたりするための小さな金属製の道具で、ふつうギザギザの部分があります。\n\n例：鍵を忘れました。",
   "audio_anime": null,
   "audio_announcer": null,
   "audio_example": null,
   "duplicate_of": null,
   "extra": "",
   "audio": {
    "aoyama": "sample/audio/home-l01-009/aoyama.mp3",
    "kyushu": "sample/audio/home-l01-009/kyushu.mp3",
    "yurei": "sample/audio/home-l01-009/yurei.mp3",
    "zunda": "sample/audio/home-l01-009/zunda.mp3",
    "no7": "sample/audio/home-l01-009/no7.mp3",
    "metan": "sample/audio/home-l01-009/metan.mp3"
   }
  },
  {
   "id": "home-l01-010",
   "front": "傘",
   "reading": "かさ",
   "meaning_zh": "伞",
   "meaning_en": "umbrella",
   "meaning_ja": "かさ",
   "explain_zh": "指用来遮雨或遮阳的便携式工具，由织物和骨架构成。\n\n例：傘を持って出かけます。\n我带着伞出门。",
   "explain_en": "A portable device used to protect against rain or sunlight, made of fabric and a frame.\n\n例：傘を持って出かけます。\nI go out with an umbrella.",
   "explain_ja": "雨や日差しを防ぐための携帯用具で、布と骨組みからできています。\n\n例：傘を持って出かけます。",
   "audio_anime": null,
   "audio_announcer": null,
   "audio_example": null,
   "duplicate_of": null,
   "extra": "",
   "audio": {
    "aoyama": "sample/audio/home-l01-010/aoyama.mp3",
    "kyushu": "sample/audio/home-l01-010/kyushu.mp3",
    "yurei": "sample/audio/home-l01-010/yurei.mp3",
    "zunda": "sample/audio/home-l01-010/zunda.mp3",
    "no7": "sample/audio/home-l01-010/no7.mp3",
    "metan": "sample/audio/home-l01-010/metan.mp3"
   }
  },
  {
   "id": "home-l01-011",
   "front": "服",
   "reading": "ふく",
   "meaning_zh": "衣服",
   "meaning_en": "clothes",
   "meaning_ja": "ふく",
   "explain_zh": "指穿在身体上用来保暖或装饰的纺织品，如衬衫、裤子等。\n\n例：新しい服を買いました。\n我买了新衣服。",
   "explain_en": "Textile items worn on the body for warmth or decoration, such as shirts and pants.\n\n例：新しい服を買いました。\nI bought new clothes.",
   "explain_ja": "体に着る、保温や装飾のための布製品で、シャツやズボンなどがあります。\n\n例：新しい服を買いました。",
   "audio_anime": null,
   "audio_announcer": null,
   "audio_example": null,
   "duplicate_of": null,
   "extra": "",
   "audio": {
    "aoyama": "sample/audio/home-l01-011/aoyama.mp3",
    "kyushu": "sample/audio/home-l01-011/kyushu.mp3",
    "yurei": "sample/audio/home-l01-011/yurei.mp3",
    "zunda": "sample/audio/home-l01-011/zunda.mp3",
    "no7": "sample/audio/home-l01-011/no7.mp3",
    "metan": "sample/audio/home-l01-011/metan.mp3"
   }
  },
  {
   "id": "home-l01-012",
   "front": "靴",
   "reading": "くつ",
   "meaning_zh": "鞋",
   "meaning_en": "shoes",
   "meaning_ja": "くつ",
   "explain_zh": "指套在脚上、用来保护脚部的东西，通常有鞋底和鞋帮。\n\n例：靴を脱いでください。\n请脱鞋。",
   "explain_en": "Items worn on the feet to protect them, typically with a sole and upper part.\n\n例：靴を脱いでください。\nPlease take off your shoes.",
   "explain_ja": "足に履いて保護するもので、ふつう底と甲の部分があります。\n\n例：靴を脱いでください。",
   "audio_anime": null,
   "audio_announcer": null,
   "audio_example": null,
   "duplicate_of": null,
   "extra": "",
   "audio": {
    "aoyama": "sample/audio/home-l01-012/aoyama.mp3",
    "kyushu": "sample/audio/home-l01-012/kyushu.mp3",
    "yurei": "sample/audio/home-l01-012/yurei.mp3",
    "zunda": "sample/audio/home-l01-012/zunda.mp3",
    "no7": "sample/audio/home-l01-012/no7.mp3",
    "metan": "sample/audio/home-l01-012/metan.mp3"
   }
  }
 ]
}
